[
    {
        "id": "e1f1ce9e.cd563",
        "type": "tab",
        "label": "Dashboard",
        "disabled": false,
        "info": ""
    },
    {
        "id": "a6a40467.0c7cf8",
        "type": "tab",
        "label": "State",
        "disabled": false,
        "info": ""
    },
    {
        "id": "bd1a651f.1d5b68",
        "type": "tab",
        "label": "History",
        "disabled": false,
        "info": ""
    },
    {
        "id": "3e6a1931.551c96",
        "type": "tab",
        "label": "Registration",
        "disabled": false,
        "info": ""
    },
    {
        "id": "8a5089a.03c5078",
        "type": "ui_base",
        "theme": {
            "name": "theme-light",
            "lightTheme": {
                "default": "#0094CE",
                "baseColor": "#0094CE",
                "baseFont": "-apple-system,BlinkMacSystemFont,Segoe UI,Roboto,Oxygen-Sans,Ubuntu,Cantarell,Helvetica Neue,sans-serif",
                "edited": true,
                "reset": false
            },
            "darkTheme": {
                "default": "#097479",
                "baseColor": "#097479",
                "baseFont": "-apple-system,BlinkMacSystemFont,Segoe UI,Roboto,Oxygen-Sans,Ubuntu,Cantarell,Helvetica Neue,sans-serif",
                "edited": false
            },
            "customTheme": {
                "name": "Untitled Theme 1",
                "default": "#4B7930",
                "baseColor": "#4B7930",
                "baseFont": "-apple-system,BlinkMacSystemFont,Segoe UI,Roboto,Oxygen-Sans,Ubuntu,Cantarell,Helvetica Neue,sans-serif"
            },
            "themeState": {
                "base-color": {
                    "default": "#0094CE",
                    "value": "#0094CE",
                    "edited": false
                },
                "page-titlebar-backgroundColor": {
                    "value": "#0094CE",
                    "edited": false
                },
                "page-backgroundColor": {
                    "value": "#fafafa",
                    "edited": false
                },
                "page-sidebar-backgroundColor": {
                    "value": "#ffffff",
                    "edited": false
                },
                "group-textColor": {
                    "value": "#1bbfff",
                    "edited": false
                },
                "group-borderColor": {
                    "value": "#ffffff",
                    "edited": false
                },
                "group-backgroundColor": {
                    "value": "#ffffff",
                    "edited": false
                },
                "widget-textColor": {
                    "value": "#111111",
                    "edited": false
                },
                "widget-backgroundColor": {
                    "value": "#0094ce",
                    "edited": false
                },
                "widget-borderColor": {
                    "value": "#ffffff",
                    "edited": false
                },
                "base-font": {
                    "value": "-apple-system,BlinkMacSystemFont,Segoe UI,Roboto,Oxygen-Sans,Ubuntu,Cantarell,Helvetica Neue,sans-serif"
                }
            },
            "angularTheme": {
                "primary": "indigo",
                "accents": "blue",
                "warn": "red",
                "background": "grey"
            }
        },
        "site": {
            "name": "Node-RED Dashboard",
            "hideToolbar": "false",
            "allowSwipe": "false",
            "lockMenu": "false",
            "allowTempTheme": "true",
            "dateFormat": "DD/MM/YYYY",
            "sizes": {
                "sx": 48,
                "sy": 48,
                "gx": 6,
                "gy": 6,
                "cx": 6,
                "cy": 6,
                "px": 0,
                "py": 0
            }
        }
    },
    {
        "id": "c5d82cfa.fe327",
        "type": "ui_tab",
        "z": "",
        "name": "Sensor Data",
        "icon": "fa-thermometer-quarter",
        "order": 1,
        "disabled": false,
        "hidden": false
    },
    {
        "id": "fdad0cfd.dd9c2",
        "type": "ui_group",
        "z": "",
        "name": "Sensor",
        "tab": "c5d82cfa.fe327",
        "order": 1,
        "disp": false,
        "width": "18",
        "collapse": false
    },
    {
        "id": "43ae93e4.3fd91c",
        "type": "ui_tab",
        "z": "",
        "name": "Sensor History",
        "icon": "fa-history",
        "order": 2,
        "disabled": false,
        "hidden": false
    },
    {
        "id": "5721af64.a940a",
        "type": "ui_group",
        "z": "",
        "name": "Group 1",
        "tab": "43ae93e4.3fd91c",
        "order": 1,
        "disp": false,
        "width": "20",
        "collapse": false
    },
    {
        "id": "6e34649.ed3139c",
        "type": "ui_tab",
        "z": "",
        "name": "Get State",
        "icon": "dashboard",
        "order": 3,
        "disabled": false,
        "hidden": false
    },
    {
        "id": "46aa02ba.2d710c",
        "type": "ui_group",
        "z": "",
        "name": "Group 1",
        "tab": "6e34649.ed3139c",
        "order": 1,
        "disp": true,
        "width": "12",
        "collapse": false
    },
    {
        "id": "7f6ed27e.cffe9c",
        "type": "function",
        "z": "e1f1ce9e.cd563",
        "name": "Body / Headers",
        "func": "temp = msg.payload.d.ambientTemp;\n\nvar date = new Date();\nvar options = { timeZone: 'Europe/Istanbul', year: 'numeric', month: '2-digit', day: '2-digit', hour: '2-digit', minute: '2-digit', second: '2-digit' };\nvar time = date.toLocaleDateString('tr-TR', options);\n\n\nmsg.payload = {'username':'user2','channel':'channel1', 'smartcontract':'cc', 'args': {'sensorID':'1', 'temp':temp,'time':time} };\nmsg.headers = {'content-type':'application/json'};\n\nreturn msg;",
        "outputs": 1,
        "noerr": 0,
        "x": 500,
        "y": 100,
        "wires": [
            [
                "fa90549d.2aee08"
            ]
        ]
    },
    {
        "id": "cb6c63e5.85f35",
        "type": "debug",
        "z": "e1f1ce9e.cd563",
        "name": "Result",
        "active": true,
        "tosidebar": true,
        "console": false,
        "tostatus": false,
        "complete": "true",
        "x": 970,
        "y": 100,
        "wires": []
    },
    {
        "id": "fa90549d.2aee08",
        "type": "http request",
        "z": "e1f1ce9e.cd563",
        "name": "Add Temperature HTTP Request",
        "method": "POST",
        "ret": "txt",
        "url": "http://rest-api:3000/api/addTemp",
        "tls": "",
        "x": 730,
        "y": 100,
        "wires": [
            [
                "cb6c63e5.85f35",
                "464f0826.5695e8"
            ]
        ]
    },
    {
        "id": "c9919bf1.11d6f8",
        "type": "http request",
        "z": "3e6a1931.551c96",
        "name": "Enroll Admin HTTP Request",
        "method": "POST",
        "ret": "txt",
        "url": "http://rest-api:3000/api/enrollAdmin",
        "tls": "",
        "x": 560,
        "y": 100,
        "wires": [
            [
                "345f659d.93547a"
            ]
        ]
    },
    {
        "id": "b3539900.f14c18",
        "type": "function",
        "z": "3e6a1931.551c96",
        "name": "Body / Headers",
        "func": "msg.payload = {\"adminName\": \"admin\", \"password\":\"adminpw\"};\nmsg.headers = {'content-type':'application/json'};\n\nreturn msg;",
        "outputs": 1,
        "noerr": 0,
        "x": 320,
        "y": 100,
        "wires": [
            [
                "c9919bf1.11d6f8"
            ]
        ]
    },
    {
        "id": "496f5868.116058",
        "type": "inject",
        "z": "3e6a1931.551c96",
        "name": "POST",
        "topic": "",
        "payload": "",
        "payloadType": "date",
        "repeat": "",
        "crontab": "",
        "once": false,
        "onceDelay": 0.1,
        "x": 130,
        "y": 100,
        "wires": [
            [
                "b3539900.f14c18"
            ]
        ]
    },
    {
        "id": "345f659d.93547a",
        "type": "debug",
        "z": "3e6a1931.551c96",
        "name": "Result",
        "active": true,
        "tosidebar": true,
        "console": false,
        "tostatus": false,
        "complete": "payload",
        "x": 790,
        "y": 100,
        "wires": []
    },
    {
        "id": "54328a52.b0dfe4",
        "type": "http request",
        "z": "3e6a1931.551c96",
        "name": "Register User HTTP Request",
        "method": "POST",
        "ret": "txt",
        "url": "http://rest-api:3000/api/registerUser",
        "tls": "",
        "x": 560,
        "y": 200,
        "wires": [
            [
                "97174517.83c658"
            ]
        ]
    },
    {
        "id": "f23ae524.bc3aa8",
        "type": "function",
        "z": "3e6a1931.551c96",
        "name": "Body / Headers",
        "func": "msg.payload = {\"adminName\": \"admin\", \"username\":\"user2\"};\nmsg.headers = {'content-type':'application/json'};\n\nreturn msg;",
        "outputs": 1,
        "noerr": 0,
        "x": 320,
        "y": 200,
        "wires": [
            [
                "54328a52.b0dfe4"
            ]
        ]
    },
    {
        "id": "eea0c091.6358f",
        "type": "inject",
        "z": "3e6a1931.551c96",
        "name": "POST",
        "topic": "",
        "payload": "",
        "payloadType": "date",
        "repeat": "",
        "crontab": "",
        "once": false,
        "onceDelay": 0.1,
        "x": 130,
        "y": 200,
        "wires": [
            [
                "f23ae524.bc3aa8"
            ]
        ]
    },
    {
        "id": "97174517.83c658",
        "type": "debug",
        "z": "3e6a1931.551c96",
        "name": "Result",
        "active": true,
        "tosidebar": true,
        "console": false,
        "tostatus": false,
        "complete": "payload",
        "x": 790,
        "y": 200,
        "wires": []
    },
    {
        "id": "3fa1e17b.0aa4de",
        "type": "http request",
        "z": "3e6a1931.551c96",
        "name": "Register Sensor HTTP Request",
        "method": "POST",
        "ret": "txt",
        "url": "http://rest-api:3000/api/registerSensor",
        "tls": "",
        "x": 570,
        "y": 300,
        "wires": [
            [
                "367ef485.a2f56c"
            ]
        ]
    },
    {
        "id": "16edd034.1b578",
        "type": "function",
        "z": "3e6a1931.551c96",
        "name": "Body / Headers",
        "func": "msg.payload = {\"username\": \"user2\", \"channel\":\"channel1\", \"smartcontract\":\"cc\", \"args\":{\"sensorID\": \"1\"} }\nmsg.headers = {'content-type':'application/json'};\n\nreturn msg;",
        "outputs": 1,
        "noerr": 0,
        "x": 320,
        "y": 300,
        "wires": [
            [
                "3fa1e17b.0aa4de"
            ]
        ]
    },
    {
        "id": "62ffa498.04034c",
        "type": "inject",
        "z": "3e6a1931.551c96",
        "name": "POST",
        "topic": "",
        "payload": "",
        "payloadType": "date",
        "repeat": "",
        "crontab": "",
        "once": false,
        "onceDelay": 0.1,
        "x": 130,
        "y": 300,
        "wires": [
            [
                "16edd034.1b578"
            ]
        ]
    },
    {
        "id": "367ef485.a2f56c",
        "type": "debug",
        "z": "3e6a1931.551c96",
        "name": "Result",
        "active": true,
        "tosidebar": true,
        "console": false,
        "tostatus": false,
        "complete": "payload",
        "x": 790,
        "y": 300,
        "wires": []
    },
    {
        "id": "464f0826.5695e8",
        "type": "ui_toast",
        "z": "e1f1ce9e.cd563",
        "position": "top right",
        "displayTime": "1",
        "highlight": "",
        "outputs": 0,
        "ok": "OK",
        "cancel": "",
        "topic": "Success",
        "name": "Notification",
        "x": 990,
        "y": 160,
        "wires": []
    },
    {
        "id": "85f887ec.0c8df8",
        "type": "comment",
        "z": "e1f1ce9e.cd563",
        "name": "Sensor A",
        "info": "",
        "x": 100,
        "y": 40,
        "wires": []
    },
    {
        "id": "abf502d0.d9e4c",
        "type": "data-generator",
        "z": "e1f1ce9e.cd563",
        "name": "",
        "field": "payload",
        "fieldType": "msg",
        "syntax": "text",
        "template": "{\"d\":{\"ambientTemp\": \"{{float 20 22 '0.00'}}\" }}",
        "x": 300,
        "y": 200,
        "wires": [
            [
                "8e600835.d4d138"
            ]
        ]
    },
    {
        "id": "3f24d823.136f88",
        "type": "inject",
        "z": "e1f1ce9e.cd563",
        "name": "",
        "topic": "",
        "payload": "",
        "payloadType": "date",
        "repeat": "",
        "crontab": "",
        "once": false,
        "onceDelay": 0.1,
        "x": 120,
        "y": 200,
        "wires": [
            [
                "abf502d0.d9e4c"
            ]
        ]
    },
    {
        "id": "8e600835.d4d138",
        "type": "json",
        "z": "e1f1ce9e.cd563",
        "name": "",
        "property": "payload",
        "action": "",
        "pretty": false,
        "x": 460,
        "y": 200,
        "wires": [
            [
                "ee3bbebf.10309",
                "7f6ed27e.cffe9c"
            ]
        ]
    },
    {
        "id": "ee3bbebf.10309",
        "type": "ui_gauge",
        "z": "e1f1ce9e.cd563",
        "name": "",
        "group": "fdad0cfd.dd9c2",
        "order": 1,
        "width": "6",
        "height": "6",
        "gtype": "gage",
        "title": "Temperature A",
        "label": "°C",
        "format": "{{msg.payload.d.ambientTemp}}",
        "min": 0,
        "max": "50",
        "colors": [
            "#00b500",
            "#e6e600",
            "#ca3838"
        ],
        "seg1": "",
        "seg2": "",
        "x": 640,
        "y": 200,
        "wires": []
    },
    {
        "id": "3b10f8b7.5beb58",
        "type": "function",
        "z": "e1f1ce9e.cd563",
        "name": "Body / Headers",
        "func": "temp = msg.payload.d.ambientTemp;\n\nvar date = new Date();\nvar options = { timeZone: 'Europe/Istanbul', year: 'numeric', month: '2-digit', day: '2-digit', hour: '2-digit', minute: '2-digit', second: '2-digit' };\nvar time = date.toLocaleDateString('tr-TR', options);\n\n\nmsg.payload = {'username':'user2','channel':'channel1', 'smartcontract':'cc', 'args': {'sensorID':'2', 'temp':temp,'time':time} };\nmsg.headers = {'content-type':'application/json'};\n\nreturn msg;",
        "outputs": 1,
        "noerr": 0,
        "x": 500,
        "y": 420,
        "wires": [
            [
                "fead5369.2a75d"
            ]
        ]
    },
    {
        "id": "71291f48.933e9",
        "type": "debug",
        "z": "e1f1ce9e.cd563",
        "name": "Result",
        "active": true,
        "tosidebar": true,
        "console": false,
        "tostatus": false,
        "complete": "true",
        "x": 970,
        "y": 420,
        "wires": []
    },
    {
        "id": "fead5369.2a75d",
        "type": "http request",
        "z": "e1f1ce9e.cd563",
        "name": "Add Temperature HTTP Request",
        "method": "POST",
        "ret": "txt",
        "url": "http://rest-api:3000/api/addTemp",
        "tls": "",
        "x": 730,
        "y": 420,
        "wires": [
            [
                "71291f48.933e9",
                "e13fb4dd.963e48"
            ]
        ]
    },
    {
        "id": "e13fb4dd.963e48",
        "type": "ui_toast",
        "z": "e1f1ce9e.cd563",
        "position": "top right",
        "displayTime": "1",
        "highlight": "",
        "outputs": 0,
        "ok": "OK",
        "cancel": "",
        "topic": "Success",
        "name": "Notification",
        "x": 990,
        "y": 480,
        "wires": []
    },
    {
        "id": "97372111.b45b8",
        "type": "data-generator",
        "z": "e1f1ce9e.cd563",
        "name": "",
        "field": "payload",
        "fieldType": "msg",
        "syntax": "text",
        "template": "{\"d\":{\"ambientTemp\": \"{{float 20 22 '0.00'}}\" }}",
        "x": 300,
        "y": 520,
        "wires": [
            [
                "c907a1a3.e80e7"
            ]
        ]
    },
    {
        "id": "8fe807f4.316a28",
        "type": "inject",
        "z": "e1f1ce9e.cd563",
        "name": "",
        "topic": "",
        "payload": "",
        "payloadType": "date",
        "repeat": "",
        "crontab": "",
        "once": false,
        "onceDelay": 0.1,
        "x": 120,
        "y": 520,
        "wires": [
            [
                "97372111.b45b8"
            ]
        ]
    },
    {
        "id": "c907a1a3.e80e7",
        "type": "json",
        "z": "e1f1ce9e.cd563",
        "name": "",
        "property": "payload",
        "action": "",
        "pretty": false,
        "x": 460,
        "y": 520,
        "wires": [
            [
                "61d0164f.1d5698",
                "3b10f8b7.5beb58"
            ]
        ]
    },
    {
        "id": "61d0164f.1d5698",
        "type": "ui_gauge",
        "z": "e1f1ce9e.cd563",
        "name": "",
        "group": "fdad0cfd.dd9c2",
        "order": 1,
        "width": "6",
        "height": "6",
        "gtype": "gage",
        "title": "Temperature B",
        "label": "°C",
        "format": "{{msg.payload.d.ambientTemp}}",
        "min": 0,
        "max": "50",
        "colors": [
            "#00b500",
            "#e6e600",
            "#ca3838"
        ],
        "seg1": "",
        "seg2": "",
        "x": 640,
        "y": 520,
        "wires": []
    },
    {
        "id": "e106de93.c1733",
        "type": "comment",
        "z": "e1f1ce9e.cd563",
        "name": "Sensor B",
        "info": "",
        "x": 100,
        "y": 360,
        "wires": []
    },
    {
        "id": "dea79ebd.0384c",
        "type": "comment",
        "z": "3e6a1931.551c96",
        "name": "Sensor A",
        "info": "",
        "x": 120,
        "y": 260,
        "wires": []
    },
    {
        "id": "a76f7531.f4e678",
        "type": "comment",
        "z": "3e6a1931.551c96",
        "name": "Sensor B",
        "info": "",
        "x": 120,
        "y": 380,
        "wires": []
    },
    {
        "id": "f686d51e.a57dd8",
        "type": "http request",
        "z": "3e6a1931.551c96",
        "name": "Register Sensor HTTP Request",
        "method": "POST",
        "ret": "txt",
        "url": "http://rest-api:3000/api/registerSensor",
        "tls": "",
        "x": 570,
        "y": 420,
        "wires": [
            [
                "9d3a9ba2.869c88"
            ]
        ]
    },
    {
        "id": "ec44437b.6f52f",
        "type": "function",
        "z": "3e6a1931.551c96",
        "name": "Body / Headers",
        "func": "msg.payload = {\"username\": \"user2\", \"channel\":\"channel1\", \"smartcontract\":\"cc\", \"args\":{\"sensorID\": \"2\"} }\nmsg.headers = {'content-type':'application/json'};\n\nreturn msg;",
        "outputs": 1,
        "noerr": 0,
        "x": 320,
        "y": 420,
        "wires": [
            [
                "f686d51e.a57dd8"
            ]
        ]
    },
    {
        "id": "a06f1575.baad78",
        "type": "inject",
        "z": "3e6a1931.551c96",
        "name": "POST",
        "topic": "",
        "payload": "",
        "payloadType": "date",
        "repeat": "",
        "crontab": "",
        "once": false,
        "onceDelay": 0.1,
        "x": 130,
        "y": 420,
        "wires": [
            [
                "ec44437b.6f52f"
            ]
        ]
    },
    {
        "id": "9d3a9ba2.869c88",
        "type": "debug",
        "z": "3e6a1931.551c96",
        "name": "Result",
        "active": true,
        "tosidebar": true,
        "console": false,
        "tostatus": false,
        "complete": "payload",
        "x": 790,
        "y": 420,
        "wires": []
    },
    {
        "id": "1860f04b.525f3",
        "type": "comment",
        "z": "3e6a1931.551c96",
        "name": "Sensor C",
        "info": "",
        "x": 120,
        "y": 500,
        "wires": []
    },
    {
        "id": "88652c1a.f5a58",
        "type": "http request",
        "z": "3e6a1931.551c96",
        "name": "Register Sensor HTTP Request",
        "method": "POST",
        "ret": "txt",
        "url": "http://rest-api:3000/api/registerSensor",
        "tls": "",
        "x": 570,
        "y": 540,
        "wires": [
            [
                "6ca1a6af.330f68"
            ]
        ]
    },
    {
        "id": "d5e1088b.f358e8",
        "type": "function",
        "z": "3e6a1931.551c96",
        "name": "Body / Headers",
        "func": "msg.payload = {\"username\": \"user2\", \"channel\":\"channel1\", \"smartcontract\":\"cc\", \"args\":{\"sensorID\": \"3\"} }\nmsg.headers = {'content-type':'application/json'};\n\nreturn msg;",
        "outputs": 1,
        "noerr": 0,
        "x": 320,
        "y": 540,
        "wires": [
            [
                "88652c1a.f5a58"
            ]
        ]
    },
    {
        "id": "ee0f6b67.28b298",
        "type": "inject",
        "z": "3e6a1931.551c96",
        "name": "POST",
        "topic": "",
        "payload": "",
        "payloadType": "date",
        "repeat": "",
        "crontab": "",
        "once": false,
        "onceDelay": 0.1,
        "x": 130,
        "y": 540,
        "wires": [
            [
                "d5e1088b.f358e8"
            ]
        ]
    },
    {
        "id": "6ca1a6af.330f68",
        "type": "debug",
        "z": "3e6a1931.551c96",
        "name": "Result",
        "active": true,
        "tosidebar": true,
        "console": false,
        "tostatus": false,
        "complete": "payload",
        "x": 790,
        "y": 540,
        "wires": []
    },
    {
        "id": "d1cfe0a6.f1086",
        "type": "http request",
        "z": "a6a40467.0c7cf8",
        "name": "Get History HTTP Request",
        "method": "POST",
        "ret": "txt",
        "url": "http://rest-api:3000/api/getAllStates",
        "tls": "",
        "x": 540,
        "y": 120,
        "wires": [
            [
                "c02572fa.d6af7"
            ]
        ]
    },
    {
        "id": "c02572fa.d6af7",
        "type": "json",
        "z": "a6a40467.0c7cf8",
        "name": "JSON to Object",
        "property": "payload",
        "action": "",
        "pretty": false,
        "x": 780,
        "y": 120,
        "wires": [
            [
                "798094d1.5a9bfc",
                "441cf5fc.2e813c"
            ]
        ]
    },
    {
        "id": "798094d1.5a9bfc",
        "type": "debug",
        "z": "a6a40467.0c7cf8",
        "name": "Result",
        "active": true,
        "tosidebar": true,
        "console": false,
        "tostatus": false,
        "complete": "payload",
        "x": 950,
        "y": 120,
        "wires": []
    },
    {
        "id": "441cf5fc.2e813c",
        "type": "template",
        "z": "a6a40467.0c7cf8",
        "name": "Template",
        "field": "style",
        "fieldType": "msg",
        "format": "html",
        "syntax": "mustache",
        "template": "table {\n    color: #333;\n    font-family: Helvetica, Arial, sans-serif;\n    width: 100%;\n    border-collapse: collapse;\n    border-spacing: 0;\n}\ntd, th {\n    border: 1px solid transparent;\n    /* No more visible border */\n    height: 30px;\n    transition: all 0.3s;\n    /* Simple transition for hover effect */\n}\nth {\n    background: #DFDFDF;\n    /* Darken header a bit */\n    font-weight: bold;\n}\ntd {\n    background: #FAFAFA;\n    text-align: center;\n}\n\n/* Cells in even rows (2,4,6...) are one color */\n\ntr:nth-child(even) td {\n    background: #F1F1F1;\n}\n\n/* Cells in odd rows (1,3,5...) are another (excludes header cells)  */\n\ntr:nth-child(odd) td {\n    background: #FEFEFE;\n}\ntr td:hover {\n    background: #666;\n    color: #FFF;\n}\n\n/* Hover cell effect! */",
        "x": 780,
        "y": 180,
        "wires": [
            [
                "e49ab402.384188"
            ]
        ]
    },
    {
        "id": "a1885d38.86bd3",
        "type": "function",
        "z": "a6a40467.0c7cf8",
        "name": "Body / Headers",
        "func": "msg.payload = {'username':'user2','channel':'channel1', 'smartcontract':'cc', \"args\": {\"startID\":\"0\", \"endID\":\"999\"} };\nmsg.headers = {'content-type':'application/json'};\n\nreturn msg;",
        "outputs": 1,
        "noerr": 0,
        "x": 300,
        "y": 120,
        "wires": [
            [
                "d1cfe0a6.f1086"
            ]
        ]
    },
    {
        "id": "e49ab402.384188",
        "type": "ui_template",
        "z": "a6a40467.0c7cf8",
        "group": "46aa02ba.2d710c",
        "name": "Table",
        "order": 1,
        "width": "12",
        "height": "4",
        "format": "<style>\n    {{msg.style}}\n</style>\n\n<table>\n  <thead>\n    <tr>\n      <th scope=\"col\">SensorID</th>\n      <th scope=\"col\">Time</th>\n      <th scope=\"col\">Temperature</th>\n      <th scope=\"col\">Outlier</th>\n      <th scope=\"col\">Stuck-at Fault</th>\n      <th scope=\"col\">SC Fault</th>\n      <th scope=\"col\">Final Temperature</th>\n    </tr>\n  </thead>\n  \n  <tr ng-repeat=\"obj in msg.payload\">\n    <td>{{ obj.Value.sensorID }}</td>\n    <td>{{ obj.Value.time }}</td>\n    <td>{{ obj.Value.temp }}</td>\n    <td>{{ obj.Value.outlier }}</td>\n    <td>{{ obj.Value.stuckatfault }}</td>\n    <td>{{ obj.Value.scfault }}</td>\n    <td>{{ obj.Value.finaltemp }}</td>\n  </tr>\n</table>",
        "storeOutMessages": false,
        "fwdInMessages": true,
        "templateScope": "local",
        "x": 950,
        "y": 180,
        "wires": [
            []
        ]
    },
    {
        "id": "f9097378.3e687",
        "type": "ui_button",
        "z": "a6a40467.0c7cf8",
        "name": "",
        "group": "46aa02ba.2d710c",
        "order": 1,
        "width": "0",
        "height": "0",
        "passthru": false,
        "label": "Get state",
        "tooltip": "",
        "color": "",
        "bgcolor": "",
        "icon": "",
        "payload": "",
        "payloadType": "str",
        "topic": "",
        "x": 100,
        "y": 120,
        "wires": [
            [
                "a1885d38.86bd3"
            ]
        ]
    },
    {
        "id": "35f41251.99c39e",
        "type": "http request",
        "z": "bd1a651f.1d5b68",
        "name": "Get History HTTP Request",
        "method": "POST",
        "ret": "txt",
        "url": "http://rest-api:3000/api/getHistory",
        "tls": "",
        "x": 520,
        "y": 100,
        "wires": [
            [
                "b33e30ff.d3311"
            ]
        ]
    },
    {
        "id": "b33e30ff.d3311",
        "type": "json",
        "z": "bd1a651f.1d5b68",
        "name": "JSON to Object",
        "property": "payload",
        "action": "",
        "pretty": false,
        "x": 760,
        "y": 100,
        "wires": [
            [
                "905cf22d.9ccaa",
                "6f6df898.aee9b8"
            ]
        ]
    },
    {
        "id": "905cf22d.9ccaa",
        "type": "debug",
        "z": "bd1a651f.1d5b68",
        "name": "Result",
        "active": true,
        "tosidebar": true,
        "console": false,
        "tostatus": false,
        "complete": "payload",
        "x": 930,
        "y": 100,
        "wires": []
    },
    {
        "id": "6f6df898.aee9b8",
        "type": "template",
        "z": "bd1a651f.1d5b68",
        "name": "Template",
        "field": "style",
        "fieldType": "msg",
        "format": "html",
        "syntax": "mustache",
        "template": "table {\n    color: #333;\n    font-family: Helvetica, Arial, sans-serif;\n    width: 100%;\n    border-collapse: collapse;\n    border-spacing: 0;\n}\ntd, th {\n    border: 1px solid transparent;\n    /* No more visible border */\n    height: 30px;\n    transition: all 0.3s;\n    /* Simple transition for hover effect */\n}\nth {\n    background: #DFDFDF;\n    /* Darken header a bit */\n    font-weight: bold;\n}\ntd {\n    background: #FAFAFA;\n    text-align: center;\n}\n\n/* Cells in even rows (2,4,6...) are one color */\n\ntr:nth-child(even) td {\n    background: #F1F1F1;\n}\n\n/* Cells in odd rows (1,3,5...) are another (excludes header cells)  */\n\ntr:nth-child(odd) td {\n    background: #FEFEFE;\n}\ntr td:hover {\n    background: #666;\n    color: #FFF;\n}\n\n/* Hover cell effect! */",
        "x": 760,
        "y": 160,
        "wires": [
            [
                "495930e1.cf74d"
            ]
        ]
    },
    {
        "id": "2de37fa6.7631a",
        "type": "function",
        "z": "bd1a651f.1d5b68",
        "name": "Body / Headers",
        "func": "msg.payload = {'username':'user2','channel':'channel1', 'smartcontract':'cc', \"args\": {\"sensorID\":\"1\"} };\nmsg.headers = {'content-type':'application/json'};\n\nreturn msg;",
        "outputs": 1,
        "noerr": 0,
        "x": 280,
        "y": 100,
        "wires": [
            [
                "35f41251.99c39e"
            ]
        ]
    },
    {
        "id": "143634ae.5cef7b",
        "type": "ui_button",
        "z": "bd1a651f.1d5b68",
        "name": "",
        "group": "5721af64.a940a",
        "order": 1,
        "width": 0,
        "height": 0,
        "passthru": false,
        "label": "Get History",
        "tooltip": "",
        "color": "",
        "bgcolor": "",
        "icon": "",
        "payload": "",
        "payloadType": "str",
        "topic": "",
        "x": 90,
        "y": 100,
        "wires": [
            [
                "2de37fa6.7631a"
            ]
        ]
    },
    {
        "id": "495930e1.cf74d",
        "type": "ui_template",
        "z": "bd1a651f.1d5b68",
        "group": "5721af64.a940a",
        "name": "Table",
        "order": 1,
        "width": "20",
        "height": "20",
        "format": "<style>\n    {{msg.style}}\n</style>\n\n<table>\n  <thead>\n    <tr>\n      <th scope=\"col\">TxId</th>\n      <th scope=\"col\">SensorID</th>\n      <th scope=\"col\">Time</th>\n      <th scope=\"col\">Temp</th>\n      <th scope=\"col\">Outlier</th>\n      <th scope=\"col\">Stuck-at Fault</th>\n      <th scope=\"col\">Spatial Correlation Fault</th>\n      <th scope=\"col\">Final Temperature</th>\n    </tr>\n  </thead>\n  \n  <tr ng-repeat=\"obj in msg.payload\">\n    <td>{{ obj.TxId }}</td>\n    <td>{{ obj.Value.sensorID }}</td>\n    <td>{{ obj.Value.time }}</td>\n    <td>{{ obj.Value.temp }}</td>\n    <td>{{ obj.Value.outlier }}</td>\n    <td>{{ obj.Value.stuckatfault }}</td>\n    <td>{{ obj.Value.scfault }}</td>\n    <td>{{ obj.Value.finaltemp }}</td>\n  </tr>\n</table>",
        "storeOutMessages": false,
        "fwdInMessages": true,
        "templateScope": "local",
        "x": 930,
        "y": 160,
        "wires": [
            []
        ]
    },
    {
        "id": "ffb40345.b69f5",
        "type": "function",
        "z": "e1f1ce9e.cd563",
        "name": "Body / Headers",
        "func": "temp = msg.payload.d.ambientTemp;\n\nvar date = new Date();\nvar options = { timeZone: 'Europe/Istanbul', year: 'numeric', month: '2-digit', day: '2-digit', hour: '2-digit', minute: '2-digit', second: '2-digit' };\nvar time = date.toLocaleDateString('tr-TR', options);\n\n\nmsg.payload = {'username':'user2','channel':'channel1', 'smartcontract':'cc', 'args': {'sensorID':'3', 'temp':temp,'time':time} };\nmsg.headers = {'content-type':'application/json'};\n\nreturn msg;",
        "outputs": 1,
        "noerr": 0,
        "x": 500,
        "y": 720,
        "wires": [
            [
                "def8d27d.b0801"
            ]
        ]
    },
    {
        "id": "1f8b1d53.ad6053",
        "type": "debug",
        "z": "e1f1ce9e.cd563",
        "name": "Result",
        "active": true,
        "tosidebar": true,
        "console": false,
        "tostatus": false,
        "complete": "true",
        "x": 970,
        "y": 720,
        "wires": []
    },
    {
        "id": "def8d27d.b0801",
        "type": "http request",
        "z": "e1f1ce9e.cd563",
        "name": "Add Temperature HTTP Request",
        "method": "POST",
        "ret": "txt",
        "url": "http://rest-api:3000/api/addTemp",
        "tls": "",
        "x": 730,
        "y": 720,
        "wires": [
            [
                "1f8b1d53.ad6053",
                "f5bd1469.a7ba78"
            ]
        ]
    },
    {
        "id": "f5bd1469.a7ba78",
        "type": "ui_toast",
        "z": "e1f1ce9e.cd563",
        "position": "top right",
        "displayTime": "1",
        "highlight": "",
        "outputs": 0,
        "ok": "OK",
        "cancel": "",
        "topic": "Success",
        "name": "Notification",
        "x": 990,
        "y": 780,
        "wires": []
    },
    {
        "id": "78c145a.8c038bc",
        "type": "data-generator",
        "z": "e1f1ce9e.cd563",
        "name": "",
        "field": "payload",
        "fieldType": "msg",
        "syntax": "text",
        "template": "{\"d\":{\"ambientTemp\": \"{{float 20 22 '0.00'}}\" }}",
        "x": 300,
        "y": 820,
        "wires": [
            [
                "6fdd00d8.d9d42"
            ]
        ]
    },
    {
        "id": "475cded.84f3b2",
        "type": "inject",
        "z": "e1f1ce9e.cd563",
        "name": "",
        "topic": "",
        "payload": "",
        "payloadType": "date",
        "repeat": "",
        "crontab": "",
        "once": false,
        "onceDelay": 0.1,
        "x": 120,
        "y": 820,
        "wires": [
            [
                "78c145a.8c038bc"
            ]
        ]
    },
    {
        "id": "6fdd00d8.d9d42",
        "type": "json",
        "z": "e1f1ce9e.cd563",
        "name": "",
        "property": "payload",
        "action": "",
        "pretty": false,
        "x": 460,
        "y": 820,
        "wires": [
            [
                "58480a68.699d24",
                "ffb40345.b69f5"
            ]
        ]
    },
    {
        "id": "58480a68.699d24",
        "type": "ui_gauge",
        "z": "e1f1ce9e.cd563",
        "name": "",
        "group": "fdad0cfd.dd9c2",
        "order": 1,
        "width": "6",
        "height": "6",
        "gtype": "gage",
        "title": "Temperature C",
        "label": "°C",
        "format": "{{msg.payload.d.ambientTemp}}",
        "min": 0,
        "max": "50",
        "colors": [
            "#00b500",
            "#e6e600",
            "#ca3838"
        ],
        "seg1": "",
        "seg2": "",
        "x": 640,
        "y": 820,
        "wires": []
    },
    {
        "id": "4428a2e8.373e5c",
        "type": "comment",
        "z": "e1f1ce9e.cd563",
        "name": "Sensor C",
        "info": "",
        "x": 100,
        "y": 660,
        "wires": []
    }
]